pinyin_to_ipa/__init__.py
pinyin_to_ipa/py.typed
pinyin_to_ipa/transcription.py
pinyin_to_ipa-1.0.0.dist-info/licenses/LICENSE
pinyin_to_ipa_app/__init__.py
pinyin_to_ipa_app/app.py
pinyin_to_ipa_app/py.typed
pinyin_to_ipa_cli/__init__.py
pinyin_to_ipa_cli/argparse_helper.py
pinyin_to_ipa_cli/cli.py
pinyin_to_ipa_cli/main.py
pinyin_to_ipa_cli/py.typed
pinyin_to_ipa-1.0.0.dist-info/METADATA
pinyin_to_ipa-1.0.0.dist-info/WHEEL
pinyin_to_ipa-1.0.0.dist-info/entry_points.txt
pinyin_to_ipa-1.0.0.dist-info/top_level.txt
pinyin_to_ipa-1.0.0.dist-info/RECORD
