Metadata-Version: 2.4
Name: pinyin-to-ipa
Version: 1.0.0
Summary: A Python library, web application, and command-line tool for transcribing Pinyin to IPA. Tone markers are attached to the vowel of each syllable.
Author: Stefan Taubert
Maintainer: Stefan Taubert
License: MIT License
Project-URL: Homepage, https://github.com/stefantaubert/pinyin-to-ipa
Project-URL: Issues, https://github.com/stefantaubert/pinyin-to-ipa/issues
Keywords: Chinese,Mandarin,Pinyin,IPA,Phonetics,Phonology,Tone,Transcription,Language,Linguistics,Speech,Romanization,Language Learning,Natural Language Processing,Grapheme-to-Phoneme
Classifier: Development Status :: 5 - Production/Stable
Classifier: Intended Audience :: Developers
Classifier: Intended Audience :: Education
Classifier: Intended Audience :: Science/Research
Classifier: License :: OSI Approved :: MIT License
Classifier: Operating System :: OS Independent
Classifier: Operating System :: MacOS
Classifier: Operating System :: POSIX
Classifier: Operating System :: POSIX :: BSD
Classifier: Operating System :: POSIX :: Linux
Classifier: Operating System :: Unix
Classifier: Operating System :: Microsoft :: Windows
Classifier: Programming Language :: Python
Classifier: Programming Language :: Python :: 3
Classifier: Programming Language :: Python :: 3.8
Classifier: Programming Language :: Python :: 3.9
Classifier: Programming Language :: Python :: 3.10
Classifier: Programming Language :: Python :: 3.11
Classifier: Programming Language :: Python :: 3.12
Classifier: Programming Language :: Python :: 3.13
Classifier: Topic :: Multimedia :: Sound/Audio
Classifier: Topic :: Multimedia :: Sound/Audio :: Analysis
Classifier: Topic :: Multimedia :: Sound/Audio :: Sound Synthesis
Classifier: Topic :: Multimedia :: Sound/Audio :: Speech
Classifier: Topic :: Text Processing :: Linguistic
Classifier: Topic :: Scientific/Engineering :: Human Machine Interfaces
Classifier: Topic :: Software Development :: Libraries :: Python Modules
Classifier: Environment :: Console
Classifier: Environment :: Web Environment
Requires-Python: <3.14,>=3.8
License-File: LICENSE
Requires-Dist: ordered-set>=4.1.0
Requires-Dist: pypinyin>=0.54
Provides-Extra: dev
Requires-Dist: pytest; extra == "dev"
Requires-Dist: pytest-cov; extra == "dev"
Requires-Dist: pytest-xdist; extra == "dev"
Requires-Dist: tox; extra == "dev"
Requires-Dist: ruff; extra == "dev"
Requires-Dist: mypy; extra == "dev"
Requires-Dist: rope; extra == "dev"
Requires-Dist: build; extra == "dev"
Requires-Dist: twine; extra == "dev"
Provides-Extra: app
Requires-Dist: gradio; extra == "app"
Dynamic: license-file
